datajunction_reflection/__about__.py
datajunction_reflection/__init__.py
datajunction_reflection/config.py
datajunction_reflection/worker/__init__.py
datajunction_reflection/worker/app.py
datajunction_reflection/worker/tasks.py
datajunction_reflection/worker/utils.py
datajunction_reflection-0.0.56.dist-info/METADATA
datajunction_reflection-0.0.56.dist-info/WHEEL
datajunction_reflection-0.0.56.dist-info/licenses/LICENSE
datajunction_reflection-0.0.56.dist-info/RECORD
