Metadata-Version: 2.4
Name: datajunction-reflection
Version: 0.0.56
Summary: OSS Implementation of a DataJunction Reflection Service
Project-URL: repository, https://github.com/DataJunction/dj
Author-email: DataJunction Authors <roberto@dealmeida.net>
License: MIT
License-File: LICENSE
Classifier: License :: OSI Approved :: MIT License
Classifier: Operating System :: OS Independent
Classifier: Programming Language :: Python :: 3.10
Classifier: Programming Language :: Python :: 3.11
Classifier: Programming Language :: Python :: 3.12
Requires-Python: <4.0,>=3.10
Requires-Dist: celery[redis]>=5.2.3
Requires-Dist: importlib-metadata
Requires-Dist: pydantic<2.0
Requires-Dist: python-dotenv==0.19.2
Requires-Dist: pytz
Requires-Dist: requests>=2.26.0
Provides-Extra: uvicorn
Requires-Dist: uvicorn[standard]>=0.21.1; extra == 'uvicorn'
